rujaion/__init__.py
rujaion/completer.py
rujaion/console.py
rujaion/custom_popup.py
rujaion/display_widget.py
rujaion/editor.py
rujaion/extract.py
rujaion/py_syntax_checker.py
rujaion/rujaion_main.py
rujaion/syntax.py
rujaion/table_view.py
rujaion/temp.py
rujaion/util.py
rujaion/webview_widget.py
rujaion/command/__init__.py
rujaion/command/finder.py
rujaion/command/login.py
rujaion/command/submit.py
rujaion/command/test.py
rujaion/resources/live_templates_cpp.xml
rujaion/resources/live_templates_rust.xml
rujaion/resources/template.cpp
rujaion/resources/template.py
rujaion/resources/template.rs
Rujaion-0.14.0.dist-info/LICENSE.txt
Rujaion-0.14.0.dist-info/METADATA
Rujaion-0.14.0.dist-info/WHEEL
Rujaion-0.14.0.dist-info/entry_points.txt
Rujaion-0.14.0.dist-info/top_level.txt
Rujaion-0.14.0.dist-info/RECORD
