Metadata-Version: 2.1
Name: Rujaion
Version: 0.14.0
Summary: 'Online judge aware Rust IDE'
Home-page: UNKNOWN
Author: Ryosuke Fukatani
License: UNKNOWN
Platform: UNKNOWN
Classifier: Development Status :: 4 - Beta
Classifier: Intended Audience :: Developers
Classifier: License :: OSI Approved :: MIT License
Classifier: Programming Language :: Python :: 3.5
Classifier: Topic :: Software Development
Classifier: Topic :: Utilities
Requires-Dist: PyQt5
Requires-Dist: PyQtWebEngine
Requires-Dist: pexpect
Requires-Dist: online-judge-tools (==11.1.1)
Requires-Dist: online-judge-api-client (==10.5.0)
Requires-Dist: pandas
